Flask_WaffleConf-0.3.1.dist-info/DESCRIPTION.rst
Flask_WaffleConf-0.3.1.dist-info/METADATA
Flask_WaffleConf-0.3.1.dist-info/RECORD
Flask_WaffleConf-0.3.1.dist-info/WHEEL
Flask_WaffleConf-0.3.1.dist-info/metadata.json
Flask_WaffleConf-0.3.1.dist-info/pbr.json
Flask_WaffleConf-0.3.1.dist-info/top_level.txt
flask_hybridconf/__init__.py
flask_hybridconf/hybrid_conf.py
flask_hybridconf/models.py
flask_hybridconf/store.py
flask_hybridconf/views.py
flask_waffleconf/__init__.py
flask_waffleconf/core.py
flask_waffleconf/models.py
flask_waffleconf/store.py
flask_waffleconf/util.py
flask_waffleconf/views.py
flask_waffleconf/waffle_conf.py
flask_waffleconf/watcher.py
flask_waffleconf/templates/waffleconf/.waffle_form.html.swp
flask_waffleconf/templates/waffleconf/waffle_form.html
