Metadata-Version: 2.0
Name: Flask-WaffleConf
Version: 0.3.1
Summary: Store variables in database and update them at runtime
Home-page: https://github.com/rmed/flask-waffleconf
Author: Rafael Medina García
Author-email: rafamedgar@gmail.com.com
License: GPLv2+
Platform: any
Classifier: Development Status :: 3 - Alpha
Classifier: Environment :: Web Environment
Classifier: Framework :: Flask
Classifier: Intended Audience :: Developers
Classifier: License :: OSI Approved :: GNU General Public License v2 or later (GPLv2+)
Classifier: Operating System :: OS Independent
Classifier: Programming Language :: Python
Classifier: Topic :: Internet :: WWW/HTTP :: Dynamic Content
Classifier: Topic :: Software Development :: Libraries :: Python Modules
Requires-Dist: Flask
